picorm/FileStorage.py
picorm/SQLiteStorage.py
picorm/Storage.py
picorm/__about__.py
picorm/__init__.py
picorm/utils.py
picorm/tests/__init__.py
picorm/tests/test_storages.py
picorm-0.1.6.dist-info/LICENSE
picorm-0.1.6.dist-info/METADATA
picorm-0.1.6.dist-info/WHEEL
picorm-0.1.6.dist-info/top_level.txt
picorm-0.1.6.dist-info/RECORD
