Metadata-Version: 2.1
Name: picorm
Version: 0.1.6
Summary: Small ORM with limited functions for multiple database engines for pet-projects
Home-page: https://github.com/k5md/picorm
Author: k5md
Author-email: k-5md@yandex.ru
License: MIT License
Project-URL: Bug Tracker, https://github.com/k5md/picorm/issues
Classifier: Programming Language :: Python :: 3
Classifier: License :: OSI Approved :: MIT License
Classifier: Operating System :: Microsoft :: Windows
Classifier: Operating System :: Unix
Classifier: Topic :: Utilities
Classifier: Topic :: Database
Classifier: Topic :: Database :: Front-Ends
Requires-Python: >=3.7
License-File: LICENSE
